scidmcli/__init__.py
scidmcli/connection.py
scidmcli/credential.py
scidmcli/download.py
scidmcli/main.py
scidmcli/util.py
scidmcli/version.py
scidmcli/cli/config.py
scidmcli/cli/dataset.py
scidmcli/cli/organization.py
scidmcli/cli/user.py
scidmcli/yaml/logging.yaml
scidmcli-0.0.6.dist-info/LICENSE
scidmcli-0.0.6.dist-info/METADATA
scidmcli-0.0.6.dist-info/WHEEL
scidmcli-0.0.6.dist-info/entry_points.txt
scidmcli-0.0.6.dist-info/top_level.txt
scidmcli-0.0.6.dist-info/RECORD
