Metadata-Version: 2.1
Name: scidmcli
Version: 0.0.6
Summary: NCHC SciDM
Author-email: WeiYu <wychen@narlabs.org.tw>
License: apache2
Keywords: ckan
Classifier: Topic :: Database :: Front-Ends
Classifier: Programming Language :: Python :: 3
Requires-Python: >=3.7
License-File: LICENSE
Requires-Dist: ckanapi
Requires-Dist: requests
Requires-Dist: configparser
Requires-Dist: click
Requires-Dist: PyYAML
Requires-Dist: terminaltables
Requires-Dist: tqdm
Requires-Dist: aiohttp
Requires-Dist: charset-normalizer ~=2.0.4
